Metadata-Version: 1.1
Name: django-html-assertions
Version: 0.1.0
Summary: A simple Django app to add html related assertions to djangos testing classes.
Home-page: https://github.com/omni-digital/django_html_assertions/
Author: Omni Digital
Author-email: dev@omni-digital.co.uk
License: MIT
Download-URL: https://github.com/omni-digital/django_html_assertions/tarball/0.1.0
Keywords: django,test,tests,testing,html,assert,assertion,assertions
Platform: UNKNOWN
Classifier: Environment :: Web Environment
Classifier: Framework :: Django
Classifier: Framework :: Django :: 1.11
Classifier: Intended Audience :: Developers
Classifier: License :: OSI Approved :: MIT License
Classifier: Operating System :: OS Independent
Classifier: Programming Language :: Python
Classifier: Programming Language :: Python :: 2
Classifier: Programming Language :: Python :: 2.7
Classifier: Programming Language :: Python :: 3
Classifier: Programming Language :: Python :: 3.4
Classifier: Programming Language :: Python :: 3.5
Classifier: Programming Language :: Python :: 3.6
Classifier: Topic :: Internet :: WWW/HTTP
Classifier: Topic :: Internet :: WWW/HTTP :: Dynamic Content
